[
     {
          "flange": {
               "name": "flange",
               "tcp": {
                    "point": {
                         "x": 0,
                         "y": 0,
                         "z": 0
                    },
                    "rotation": {
                         "roll": 0,
                         "pitch": 0,
                         "yaw": 0
                    },
                    "blend": 0.0,
                    "actions": null
               }
          },
          "tcp_kfc_n": {
               "name": "unnamed_tool",
               "tcp": {
                    "point": {
                         "x": -0.1288654783666489,
                         "y": 0.11213809746112628,
                         "z": 0.0862373311442368
                    },
                    "rotation": {
                         "roll": 1.5804860630389423,
                         "pitch": 0.7785004579811691,
                         "yaw": 1.4872322767910213
                    },
                    "blend": 0.0,
                    "actions": null
               }
          },
          "skin_am_10ml": {
               "name": "unnamed_tool",
               "tcp": {
                    "point": {
                         "x": -0.16793538812593858,
                         "y": 0.06509163323700859,
                         "z": 0.04751834151530443
                    },
                    "rotation": {
                         "roll": 0,
                         "pitch": 0,
                         "yaw": 0
                    },
                    "blend": 0.0,
                    "actions": null
               }
          }
     },
     {
          "base_def": {
               "point": {
                    "x": 0.0,
                    "y": 0.0,
                    "z": 0.0
               },
               "rotation": {
                    "roll": 0.0,
                    "pitch": 0.0,
                    "yaw": 0.0
               },
               "blend": 0.0,
               "actions": null
          },
          "b_0304": {
               "point": {
                    "x": -0.3941393402815418,
                    "y": 0.28904376745523885,
                    "z": -0.05420252891808605
               },
               "rotation": {
                    "roll": -0.011004026673208054,
                    "pitch": 0.001298667741267602,
                    "yaw": -3.133652255529866
               },
               "blend": 0.0,
               "actions": null
          },
          "b0404_1": {
               "point": {
                    "x": -0.3953725409403683,
                    "y": 0.28792600723775474,
                    "z": -0.03987928932695638
               },
               "rotation": {
                    "roll": -0.00944429094267958,
                    "pitch": 0.0009346744786072804,
                    "yaw": -3.133898459952982
               },
               "blend": 0.0,
               "actions": null
          },
          "work_0706": {
               "point": {
                    "x": -0.21837200957968475,
                    "y": -0.2395121402280241,
                    "z": -0.033856325470241956
               },
               "rotation": {
                    "roll": -0.014569645141790757,
                    "pitch": -0.0058083722349503205,
                    "yaw": -1.565883288101076
               },
               "blend": 0.0,
               "actions": null
          }
     },
     {
          "home": {
               "angles": [
                    0.0,
                    -90.0,
                    0.0,
                    0.0,
                    0.0,
                    0.0
               ],
               "timestamp": "2022-12-26T05:17:18.943252Z"
          },
          "home_1": {
               "angles": [
                    0.0,
                    -90.0,
                    0.0,
                    0.0,
                    0.0,
                    90.0
               ],
               "timestamp": "2022-12-26T05:17:18.943252Z"
          },
          "wp2812_1": {
               "angles": [
                    -40.137611389160156,
                    -79.304443359375,
                    113.89175415039062,
                    -34.17172622680664,
                    143.69761657714844,
                    -223.05503845214844
               ],
               "timestamp": "2022-12-28T06:54:11.781161Z"
          },
          "relax_p2812_1": {
               "angles": [
                    -72.37406158447266,
                    -48.7158203125,
                    130.81246948242188,
                    -67.77441024780273,
                    170.84539794921875,
                    -119.50172424316406
               ],
               "timestamp": "2022-12-28T06:53:28.862851Z"
          },
          "wp0306_1": {
               "angles": [
                    -41.543052673339844,
                    -80.61637878417969,
                    115.07684326171875,
                    -32.49262619018555,
                    135.9538116455078,
                    -244.1670684814453
               ],
               "timestamp": "2023-06-03T05:26:24.368088Z"
          },
          "scan_pos_0506": {
               "angles": [
                    -42.604225158691406,
                    -72.33236694335938,
                    99.1322021484375,
                    3.0156707763671875,
                    130.9237518310547,
                    -224.30616760253906
               ],
               "timestamp": "2023-06-05T10:50:42.431955Z"
          },
          "relax_0506": {
               "angles": [
                    -6.299537658691406,
                    -20.111663818359375,
                    116.57623291015625,
                    -184.31338500976562,
                    136.8987579345703,
                    -335.0283203125
               ],
               "timestamp": "2023-06-05T11:32:21.246003Z"
          }
     },
     {
          "kfc_tcp_n_1": {
               "point": {
                    "x": -0.25568175715365243,
                    "y": 0.24151980071483498,
                    "z": 0.2185842806795608
               },
               "rotation": {
                    "roll": -1.5814746024585122,
                    "pitch": -0.06436331564539645,
                    "yaw": -0.8330528673312546
               },
               "timestamp": "2023-04-03T10:42:09.652316Z"
          },
          "kfc_tcp_n_2": {
               "point": {
                    "x": -0.0728098896373711,
                    "y": 0.32526283752361246,
                    "z": 0.03943734466318226
               },
               "rotation": {
                    "roll": -1.4990537417411833,
                    "pitch": -0.46470808514472955,
                    "yaw": 0.7632374551436447
               },
               "timestamp": "2023-04-03T10:44:34.942205Z"
          },
          "kfc_tcp_n_3": {
               "point": {
                    "x": -0.41810929893756976,
                    "y": 0.3345159981863155,
                    "z": 0.1595504112635305
               },
               "rotation": {
                    "roll": -1.5773029177694462,
                    "pitch": 0.6467097383788245,
                    "yaw": -1.6993471980428863
               },
               "timestamp": "2023-04-03T10:49:53.585758Z"
          },
          "kfc_tcp_n_4": {
               "point": {
                    "x": -0.37360927863780713,
                    "y": 0.17945471021462586,
                    "z": 0.10575624206042727
               },
               "rotation": {
                    "roll": 2.188573396282158,
                    "pitch": 1.348081668092714,
                    "yaw": 2.94780933874755
               },
               "timestamp": "2023-04-03T10:55:10.550963Z"
          },
          "b0404a": {
               "point": {
                    "x": -0.39310779967416554,
                    "y": 0.2913230335146128,
                    "z": 0.03752782261098772
               },
               "rotation": {
                    "roll": -0.02057335942621037,
                    "pitch": -0.06960119562008064,
                    "yaw": 1.5602003949696104
               },
               "timestamp": "2023-04-04T05:36:44.661428Z"
          },
          "b0404b": {
               "point": {
                    "x": -0.5928975471101833,
                    "y": 0.2897876136468482,
                    "z": 0.03772907075482654
               },
               "rotation": {
                    "roll": -0.02071693335324817,
                    "pitch": -0.07009319215597108,
                    "yaw": 1.5606629505472565
               },
               "timestamp": "2023-04-04T05:37:20.543868Z"
          },
          "b0404c": {
               "point": {
                    "x": -0.5951643694436644,
                    "y": 0.1399698679610808,
                    "z": 0.03914615403887739
               },
               "rotation": {
                    "roll": -0.030631861857360772,
                    "pitch": -0.07020357828239533,
                    "yaw": 1.560832275641674
               },
               "timestamp": "2023-04-04T05:37:50.853428Z"
          },
          "b0404_st": {
               "point": {
                    "x": -0.0010529695601771763,
                    "y": 0.0019711550523168614,
                    "z": -0.0007160937537188661
               },
               "rotation": {
                    "roll": -0.013593240198098185,
                    "pitch": -0.020652835812190132,
                    "yaw": -1.7060773924629282
               },
               "timestamp": "2023-04-04T05:54:10.670818Z"
          },
          "def_st_1": {
               "point": {
                    "x": -0.38111443633808506,
                    "y": 0.20280110684278363,
                    "z": 0.20967928942719452
               },
               "rotation": {
                    "roll": -1.574908188575614,
                    "pitch": 0.06579246071167902,
                    "yaw": -0.7567157576085225
               },
               "timestamp": "2023-05-24T05:21:36.581839Z"
          },
          "skin_am_10ml_tcp_1": {
               "point": {
                    "x": -0.3701122452606144,
                    "y": 0.0936915469696267,
                    "z": 0.22595463362541965
               },
               "rotation": {
                    "roll": -1.5940218697167754,
                    "pitch": -0.04487517352958597,
                    "yaw": -1.1450742662607476
               },
               "timestamp": "2023-06-07T05:17:07.966218Z"
          },
          "skin_am_10ml_tcp_2": {
               "point": {
                    "x": -0.3703608202550673,
                    "y": 0.27868925669076544,
                    "z": 0.16549672186300213
               },
               "rotation": {
                    "roll": -2.6977314089170896,
                    "pitch": 0.025861822449934145,
                    "yaw": -1.1370636578454718
               },
               "timestamp": "2023-06-07T05:19:12.961653Z"
          },
          "skin_am_10ml_tcp_3": {
               "point": {
                    "x": -0.2763258186953169,
                    "y": 0.0026272233179941255,
                    "z": 0.1213223553588426
               },
               "rotation": {
                    "roll": -3.005719241081496,
                    "pitch": 0.3854983335056823,
                    "yaw": 1.1111070400999017
               },
               "timestamp": "2023-06-07T05:21:52.988108Z"
          },
          "skin_am_10ml_tcp_4": {
               "point": {
                    "x": -0.49004192296248217,
                    "y": 0.14757560724868563,
                    "z": 0.19532146158260616
               },
               "rotation": {
                    "roll": -2.6059163426140546,
                    "pitch": -0.5585672753310239,
                    "yaw": -2.2781452477944493
               },
               "timestamp": "2023-06-07T05:24:54.083214Z"
          },
          "work_0706_1": {
               "point": {
                    "x": -0.2379166645796098,
                    "y": 0.21975676353966897,
                    "z": 0.036073206853689255
               },
               "rotation": {
                    "roll": -1.6196475079836705,
                    "pitch": -0.004730181045067309,
                    "yaw": -1.1927570492589394
               },
               "timestamp": "2023-06-07T06:21:40.678225Z"
          },
          "work_0706_2": {
               "point": {
                    "x": -0.23817488744066706,
                    "y": 0.2723103136301267,
                    "z": 0.03530596606416564
               },
               "rotation": {
                    "roll": -1.6207900515933438,
                    "pitch": -0.0040945351310031925,
                    "yaw": -1.1935796352489203
               },
               "timestamp": "2023-06-07T06:22:39.192955Z"
          },
          "work_0706_3": {
               "point": {
                    "x": -0.3003209854375939,
                    "y": 0.271591967441873,
                    "z": 0.03495542280837724
               },
               "rotation": {
                    "roll": -1.6213001298005845,
                    "pitch": -0.004582233410339349,
                    "yaw": -1.1940336891216394
               },
               "timestamp": "2023-06-07T06:23:10.761457Z"
          }
     }
]